<?xml version="1.0" encoding="utf-8" ?>
<T3DataStructure>
	<meta>
		<langDisable>1</langDisable>
	</meta>
	<sheets>
		<sDEF>
			<ROOT>
				<TCEforms>
					<sheetTitle>LLL:EXT:bm_image_gallery/Resources/Private/Language/locallang_be.xlf:ffds.sheet_label_setup</sheetTitle>
				</TCEforms>
				<type>array</type>
				<el>
					<switchableControllerActions>
						<TCEforms>
							<label>LLL:EXT:bm_image_gallery/Resources/Private/Language/locallang_be.xlf:ffds.display_mode</label>
							<onChange>reload</onChange>
							<config>
								<type>select</type>
								<renderType>selectSingle</renderType>
								<items>
									<numIndex index="1" type="array">
										<numIndex index="0">LLL:EXT:bm_image_gallery/Resources/Private/Language/locallang_be.xlf:ffds.display_mode.1</numIndex>
										<numIndex index="1">List->list;List->gallery</numIndex>
									</numIndex>
									<numIndex index="2" type="array">
										<numIndex index="0">LLL:EXT:bm_image_gallery/Resources/Private/Language/locallang_be.xlf:ffds.display_mode.2</numIndex>
										<numIndex index="1">List->gallery</numIndex>
									</numIndex>
									<numIndex index="3" type="array">
										<numIndex index="0">LLL:EXT:bm_image_gallery/Resources/Private/Language/locallang_be.xlf:ffds.display_mode.3</numIndex>
										<numIndex index="1">List->selectedGallery</numIndex>
									</numIndex>
								</items>
							</config>
						</TCEforms>
					</switchableControllerActions>

					<settings.collections>
						<TCEforms>
							<label>LLL:EXT:bm_image_gallery/Resources/Private/Language/locallang_be.xlf:ffds.file_collections</label>
							<displayCond>
								<OR>
									<numIndex index="0"><![CDATA[FIELD:sDEF.switchableControllerActions:=:List->list;List->gallery]]></numIndex>
									<numIndex index="1"><![CDATA[FIELD:sDEF.switchableControllerActions:=:]]></numIndex>
								</OR>
							</displayCond>
							<config type="array">
								<type>group</type>
								<internal_type>db</internal_type>
								<localizeReferencesAtParentLocalization type="boolean">1</localizeReferencesAtParentLocalization>
								<allowed>sys_file_collection</allowed>
								<foreign_table>sys_file_collection</foreign_table>
								<maxitems type="integer">999</maxitems>
								<minitems type="integer">1</minitems>
								<size type="integer">5</size>
							</config>
						</TCEforms>
					</settings.collections>

					<settings.mode>
						<TCEforms>
							<label>LLL:EXT:bm_image_gallery/Resources/Private/Language/locallang_be.xlf:ffds.mode</label>
							<displayCond>
								<OR>
									<numIndex index="0"><![CDATA[FIELD:sDEF.switchableControllerActions:=:List->list;List->gallery]]></numIndex>
									<numIndex index="1"><![CDATA[FIELD:sDEF.switchableControllerActions:=:]]></numIndex>
								</OR>
							</displayCond>
							<onChange>reload</onChange>
							<config type="array">
								<type>select</type>
								<renderType>selectSingle</renderType>
								<items>
									<numIndex index="1" type="array">
										<numIndex index="0">LLL:EXT:bm_image_gallery/Resources/Private/Language/locallang_be.xlf:ffds.mode.1</numIndex>
										<numIndex index="1">0</numIndex>
									</numIndex>
									<numIndex index="2" type="array">
										<numIndex index="0">LLL:EXT:bm_image_gallery/Resources/Private/Language/locallang_be.xlf:ffds.mode.2</numIndex>
										<numIndex index="1">1</numIndex>
									</numIndex>
									<numIndex index="3" type="array">
										<numIndex index="0">LLL:EXT:bm_image_gallery/Resources/Private/Language/locallang_be.xlf:ffds.mode.3</numIndex>
										<numIndex index="1">2</numIndex>
									</numIndex>
								</items>
							</config>
						</TCEforms>
					</settings.mode>

					<settings.galleryPage>
						<TCEforms>
							<label>LLL:EXT:bm_image_gallery/Resources/Private/Language/locallang_be.xlf:ffds.gallery_page</label>
							<displayCond>
								<AND>
									<numIndex index="0"><![CDATA[FIELD:sDEF.settings.mode:=:1]]></numIndex>
									<numIndex index="1"><![CDATA[FIELD:sDEF.switchableControllerActions:=:List->list;List->gallery]]></numIndex>
								</AND>
							</displayCond>
							<config>
								<type>group</type>
								<internal_type>db</internal_type>
								<allowed>pages</allowed>
								<size>1</size>
								<maxitems>1</maxitems>
								<minitems>0</minitems>
								<show_thumbs>1</show_thumbs>
								<wizards>
									<suggest>
										<type>suggest</type>
									</suggest>
								</wizards>
							</config>
						</TCEforms>
					</settings.galleryPage>

					<settings.collection>
						<TCEforms>
							<label>LLL:EXT:bm_image_gallery/Resources/Private/Language/locallang_be.xlf:ffds.file_collection</label>
							<displayCond><![CDATA[FIELD:sDEF.switchableControllerActions:=:List->selectedGallery]]></displayCond>
							<config type="array">
								<type>group</type>
								<internal_type>db</internal_type>
								<localizeReferencesAtParentLocalization type="boolean">1</localizeReferencesAtParentLocalization>
								<allowed>sys_file_collection</allowed>
								<foreign_table>sys_file_collection</foreign_table>
								<maxitems type="integer">1</maxitems>
								<minitems type="integer">1</minitems>
								<size type="integer">1</size>
							</config>
						</TCEforms>
					</settings.collection>
				</el>
			</ROOT>
		</sDEF>
		<list>
			<ROOT>
				<TCEforms>
					<sheetTitle>LLL:EXT:bm_image_gallery/Resources/Private/Language/locallang_be.xlf:ffds.sheet_label_gallery</sheetTitle>
					<displayCond>
						<OR>
							<numIndex index="0"><![CDATA[FIELD:sDEF.switchableControllerActions:=:List->selectedGallery]]></numIndex>
							<numIndex index="1"><![CDATA[FIELD:sDEF.settings.mode:!=:1]]></numIndex>
						</OR>
					</displayCond>
				</TCEforms>
				<type>array</type>
				<el>
					<settings.maxItems>
						<TCEforms>
							<label>LLL:EXT:bm_image_gallery/Resources/Private/Language/locallang_be.xlf:ffds.maxItems</label>
							<config>
								<type>input</type>
								<size>5</size>
								<eval>trim,int</eval>
								<range>
									<lower>0</lower>
								</range>
								<default>0</default>
							</config>
						</TCEforms>
					</settings.maxItems>

					<settings.orderBy>
						<TCEforms>
							<label>LLL:EXT:bm_image_gallery/Resources/Private/Language/locallang_be.xlf:ffds.orderBy</label>
							<config>
								<type>select</type>
								<renderType>selectSingle</renderType>
								<items type="array">
									<numIndex index="0" type="array">
										<numIndex index="0">LLL:EXT:bm_image_gallery/Resources/Private/Language/locallang_be.xlf:ffds.orderBy.default</numIndex>
										<numIndex index="1">default</numIndex>
									</numIndex>
									<numIndex index="1" type="array">
										<numIndex index="0">LLL:EXT:bm_image_gallery/Resources/Private/Language/locallang_be.xlf:ffds.orderBy.name</numIndex>
										<numIndex index="1">name</numIndex>
									</numIndex>
									<numIndex index="2" type="array">
										<numIndex index="0">LLL:EXT:bm_image_gallery/Resources/Private/Language/locallang_be.xlf:ffds.orderBy.creationDate</numIndex>
										<numIndex index="1">creation_date</numIndex>
									</numIndex>
									<numIndex index="3" type="array">
										<numIndex index="0">LLL:EXT:bm_image_gallery/Resources/Private/Language/locallang_be.xlf:ffds.orderBy.modificationDate</numIndex>
										<numIndex index="1">modification_date</numIndex>
									</numIndex>
								</items>
							</config>
						</TCEforms>
					</settings.orderBy>

					<settings.sortingOrder>
						<TCEforms>
							<label>LLL:EXT:bm_image_gallery/Resources/Private/Language/locallang_be.xml:ffds.sortingOrder</label>
							<config>
								<type>select</type>
								<renderType>selectSingle</renderType>
								<items type="array">
									<numIndex index="0" type="array">
										<numIndex index="0">LLL:EXT:bm_image_gallery/Resources/Private/Language/locallang_be.xml:ffds.sortingOrder.ascending</numIndex>
										<numIndex index="1">ascending</numIndex>
									</numIndex>
									<numIndex index="1" type="array">
										<numIndex index="0">LLL:EXT:bm_image_gallery/Resources/Private/Language/locallang_be.xml:ffds.sortingOrder.descending</numIndex>
										<numIndex index="1">descending</numIndex>
									</numIndex>
									<numIndex index="2" type="array">
										<numIndex index="0">LLL:EXT:bm_image_gallery/Resources/Private/Language/locallang_be.xml:ffds.sortingOrder.random</numIndex>
										<numIndex index="1">random</numIndex>
									</numIndex>
								</items>
							</config>
						</TCEforms>
					</settings.sortingOrder>
				</el>
			</ROOT>
		</list>
	</sheets>
</T3DataStructure>